keychain_access/__init__.py
keychain_access/core.py
keychain_access/exceptions.py
keychain_access/py.typed
keychain_access-1.0.0.dist-info/METADATA
keychain_access-1.0.0.dist-info/WHEEL
keychain_access-1.0.0.dist-info/licenses/LICENSE
keychain_access-1.0.0.dist-info/RECORD
