Metadata-Version: 2.4
Name: keychain-access
Version: 1.0.0
Summary: Access to the OSX Keychain API in Python.
Author-email: Max Muoto <maxmuoto@gmail.com>
License: MIT License
License-File: LICENSE
Requires-Python: <3.14,>=3.9
Requires-Dist: pyobjc<12.0.0,>=10.0.0
